vapour_linux_amd64
