Metadata-Version: 1.0
Name: vapour-linux-amd64
Version: 0.2.1
Summary: This package contains binary executable dependencies for the master.
Home-page: UNKNOWN
Author: VapourApps
Author-email: vapour@vapour.com
License: UNKNOWN
Platform: UNKNOWN
